echo/__init__.py
echo/server.py
grpcWSGI/__init__.py
grpcWSGI/__version__.py
grpcWSGI/client.py
grpcWSGI/protocol.py
grpcWSGI/server.py
grpcWSGI-0.0.4.dist-info/LICENSE
grpcWSGI-0.0.4.dist-info/METADATA
grpcWSGI-0.0.4.dist-info/WHEEL
grpcWSGI-0.0.4.dist-info/top_level.txt
grpcWSGI-0.0.4.dist-info/RECORD
