Metadata-Version: 2.1
Name: grpcWSGI
Version: 0.0.4
Summary: gRPC-Web + WSGI
Home-page: https://github.com/public/grpcWSGI
Author: Alex Stapleton
Author-email: alexs@prol.etari.at
License: MIT
Platform: UNKNOWN
Classifier: License :: OSI Approved :: MIT License
Classifier: Programming Language :: Python
Classifier: Programming Language :: Python :: 3
Classifier: Programming Language :: Python :: 3.6
Classifier: Programming Language :: Python :: Implementation :: CPython
Classifier: Programming Language :: Python :: Implementation :: PyPy
Requires-Python: >=3.6.0
Requires-Dist: grpcio
Requires-Dist: requests
